.dada-version
MANIFEST.in
README.md
requirements.txt
setup.cfg
setup.py
dada_archive/__init__.py
dada_archive.egg-info/PKG-INFO
dada_archive.egg-info/SOURCES.txt
dada_archive.egg-info/dependency_links.txt
dada_archive.egg-info/requires.txt
dada_archive.egg-info/top_level.txt
dada_archive/tests/__init__.py
dada_archive/tests/test_archive.py